SimproAPI/Exceptions.py
SimproAPI/OAuth2.py
SimproAPI/Sessions.py
SimproAPI/TokenManager.py
SimproAPI/Trackables.py
SimproAPI/__init__.py
SimproAPI-0.1.8.dist-info/LICENSE
SimproAPI-0.1.8.dist-info/METADATA
SimproAPI-0.1.8.dist-info/WHEEL
SimproAPI-0.1.8.dist-info/top_level.txt
SimproAPI-0.1.8.dist-info/RECORD
