Metadata-Version: 2.1
Name: SimproAPI
Version: 0.1.8
Summary: Structured way to interface with Simpro
Home-page: https://github.com/Razmo99/SimproAPI
Author: razmo99
Author-email: lewis.munro@live.com
License: MIT License
Keywords: Simpro,API,SimproAPI
Platform: UNKNOWN
Classifier: Development Status :: 1 - Planning
Classifier: Intended Audience :: Developers
Classifier: License :: OSI Approved :: MIT License
Classifier: Operating System :: OS Independent
Classifier: Programming Language :: Python :: 3.8
Classifier: Programming Language :: Python :: 3.9
Requires-Python: ~=3.8
Requires-Dist: requests (>=2.24.0)
Requires-Dist: urllib3 (>=1.25.10)
